foliant/preprocessors/metagraph/__init__.py
foliant/preprocessors/metagraph/draw.py
foliant/preprocessors/metagraph/metagraph.py
foliantcontrib.metagraph-0.1.3.dist-info/LICENSE
foliantcontrib.metagraph-0.1.3.dist-info/METADATA
foliantcontrib.metagraph-0.1.3.dist-info/WHEEL
foliantcontrib.metagraph-0.1.3.dist-info/top_level.txt
foliantcontrib.metagraph-0.1.3.dist-info/RECORD
