Metadata-Version: 2.1
Name: foliantcontrib.metagraph
Version: 0.1.3
Summary: Preprocessor which generates schemes from metadata
Home-page: UNKNOWN
Author: Daniil Minukhin
Author-email: ddddsa@gmail.com
License: MIT
Platform: any
Classifier: Development Status :: 5 - Production/Stable
Classifier: Environment :: Console
Classifier: Intended Audience :: Developers
Classifier: License :: OSI Approved :: MIT License
Classifier: Operating System :: OS Independent
Classifier: Programming Language :: Python
Classifier: Topic :: Documentation
Classifier: Topic :: Utilities
Requires-Dist: foliant (>=1.0.5)
Requires-Dist: foliantcontrib.meta (>=1.3.1)
Requires-Dist: foliantcontrib.utils (>=1.0.2)
